README.rst
config_sample.yml
setup.py
py_qualtrics_api/__init__.py
py_qualtrics_api/tools.py
py_qualtrics_api.egg-info/PKG-INFO
py_qualtrics_api.egg-info/SOURCES.txt
py_qualtrics_api.egg-info/dependency_links.txt
py_qualtrics_api.egg-info/requires.txt
py_qualtrics_api.egg-info/top_level.txt