Metadata-Version: 1.1
Name: py-qualtrics-api
Version: 0.2.9
Summary: Library for facilitating survey administration with Qualtrics. Requires Qualtrics API.
Home-page: https://github.com/cwade/py_qualtrics_api
Author: cwade
Author-email: pysurveyhelper@gmail.com
License: MIT
Keywords: python qualtrics api survey_administration
Platform: UNKNOWN
Classifier: Development Status :: 3 - Alpha
Classifier: Intended Audience :: Developers
Classifier: License :: OSI Approved :: MIT License
Classifier: Programming Language :: Python :: 3
Classifier: Programming Language :: Python :: 3.2
Classifier: Programming Language :: Python :: 3.3
Classifier: Programming Language :: Python :: 3.4
Classifier: Programming Language :: Python :: 3.5
Classifier: Programming Language :: Python :: 3.6
Classifier: Programming Language :: Python :: 3.7
